LICENSE
README.md
pyproject.toml
setup.py
tencirchem/__init__.py
tencirchem/constants.py
tencirchem/molecule.py
tencirchem.egg-info/PKG-INFO
tencirchem.egg-info/SOURCES.txt
tencirchem.egg-info/dependency_links.txt
tencirchem.egg-info/requires.txt
tencirchem.egg-info/top_level.txt
tencirchem/applications/__init__.py
tencirchem/applications/vbe_lib.py
tencirchem/dynamic/__init__.py
tencirchem/dynamic/time_derivative.py
tencirchem/dynamic/time_evolution.py
tencirchem/dynamic/transform.py
tencirchem/dynamic/model/__init__.py
tencirchem/dynamic/model/pyrazine.py
tencirchem/dynamic/model/sbm.py
tencirchem/static/__init__.py
tencirchem/static/ci_utils.py
tencirchem/static/engine_hea.py
tencirchem/static/engine_ucc.py
tencirchem/static/evolve_civector.py
tencirchem/static/evolve_pyscf.py
tencirchem/static/evolve_statevector.py
tencirchem/static/evolve_tensornetwork.py
tencirchem/static/hamiltonian.py
tencirchem/static/hea.py
tencirchem/static/kupccgsd.py
tencirchem/static/puccd.py
tencirchem/static/ucc.py
tencirchem/static/uccsd.py
tencirchem/utils/__init__.py
tencirchem/utils/backend.py
tencirchem/utils/circuit.py
tencirchem/utils/misc.py
tencirchem/utils/optimizer.py
tests/__init__.py
tests/test_misc.py
tests/dynamics/__init__.py
tests/dynamics/test_dynamics.py
tests/dynamics/test_hamiltonian.py
tests/static/__init__.py
tests/static/test_engine.py
tests/static/test_hamiltonian.py
tests/static/test_hea.py
tests/static/test_molecule.py
tests/static/test_optimizer.py
tests/static/test_puccd.py
tests/static/test_static.py