Metadata-Version: 2.1
Name: tencirchem
Version: 2024.11
Summary: Efficient quantum computational chemistry based on TensorCircuit
Home-page: https://github.com/tencent-quantum-lab/tencirchem
Author: TenCirChem Authors
Author-email: liw31@163.com
License: UNKNOWN
Platform: UNKNOWN
Classifier: Programming Language :: Python :: 3
Classifier: Operating System :: OS Independent
Requires-Python: >=3.9
Provides-Extra: jax
